tensorboard_plugin_fairness_indicators/__init__.py
tensorboard_plugin_fairness_indicators/demo.py
tensorboard_plugin_fairness_indicators/metadata.py
tensorboard_plugin_fairness_indicators/metadata_test.py
tensorboard_plugin_fairness_indicators/plugin.py
tensorboard_plugin_fairness_indicators/plugin_test.py
tensorboard_plugin_fairness_indicators/summary_v2.py
tensorboard_plugin_fairness_indicators/summary_v2_test.py
tensorboard_plugin_fairness_indicators/version.py
tensorboard_plugin_fairness_indicators/static/index.js
tensorboard_plugin_fairness_indicators-0.48.0.dist-info/METADATA
tensorboard_plugin_fairness_indicators-0.48.0.dist-info/WHEEL
tensorboard_plugin_fairness_indicators-0.48.0.dist-info/entry_points.txt
tensorboard_plugin_fairness_indicators-0.48.0.dist-info/top_level.txt
tensorboard_plugin_fairness_indicators-0.48.0.dist-info/RECORD
